setup.py
plotformatter/__init__.py
plotformatter/_base.py
plotformatter/test.py
plotformatter.egg-info/PKG-INFO
plotformatter.egg-info/SOURCES.txt
plotformatter.egg-info/dependency_links.txt
plotformatter.egg-info/not-zip-safe
plotformatter.egg-info/top_level.txt