Metadata-Version: 1.0
Name: plotformatter
Version: 0.1.0
Summary: Creates matplotlib and seaborn visuals
Home-page: https://github.com/ajgiust/plotformatter
Author: Anthony Giustino
Author-email: UNKNOWN
License: UNKNOWN
Platform: UNKNOWN
